message_app_server-0.0.2.data/scripts/server_run
server/__init__.py
server/add_user.py
server/config_window.py
server/constants.py
server/core.py
server/descriptors.py
server/errors.py
server/main_window.py
server/metaclasses.py
server/remove_user.py
server/server.py
server/server_database.py
server/server_run.py
server/stat_window.py
server/utils.py
server/logs/__init__.py
server/logs/config_client_log.py
server/logs/config_server_log.py
server/logs/decos.py
server/sphinx/__init__.py
server/sphinx/source/__init__.py
server/sphinx/source/conf.py
message_app_server-0.0.2.dist-info/METADATA
message_app_server-0.0.2.dist-info/WHEEL
message_app_server-0.0.2.dist-info/top_level.txt
message_app_server-0.0.2.dist-info/RECORD
